{
  "scripts": {
    "com.r2studio.EndlessFrontier": {
      "title": "Endless Frontier AutoPlay",
      "versionCode": 18,
      "description": "<h1>無盡的邊疆自動玩</h1><ul><li>提升穩定性</li><li>新增升級全體士兵</li><li>新增購買全體士兵</li><li>修正卡在任務資訊</li></ul>",
      "packageName": "com.ekkorr.endlessfrontier.global",
      "downloadURL": "https://github.com/r2-studio/robotmon-scripts/raw/master/scripts/com.r2studio.EndlessFrontier/index.zip",
      "dependencies": [
        "https://github.com/r2-studio/robotmon-scripts/raw/master/libs/TaskController-0.0.1.js"
      ]
    },
    "com.r2studio.Tsum": {
      "title": "Tsum Tsum AutoPlay",
      "versionCode": 36,
      "description": "<ul><li>⚠️ Should update Robotmon app and restart service\n</li><li>⭐ New Quick Play Mode(新增快速計算模式)\n</li><li>Supported more skills</li><li>Bubble item</li></ul>",
      "packageName": "com.linecorp.LGTMTMG",
      "downloadURL": "https://github.com/r2-studio/robotmon-scripts/raw/master/scripts/com.r2studio.Tsum/index.zip"
    },
    "com.r2studio.MarvelFutureFight": {
      "title": "Marvel Future Fight AutoPlay",
      "versionCode": 6,
      "packageName": "com.netmarble.mherosgb",
      "downloadURL": "https://github.com/r2-studio/robotmon-scripts/raw/master/scripts/com.r2studio.MarvelFutureFight/index.zip",
      "dependencies": [
        "https://github.com/r2-studio/robotmon-scripts/raw/master/libs/RBM-0.0.1.js",
        "https://github.com/r2-studio/robotmon-scripts/raw/master/libs/TaskController-0.0.1.js"
      ]
    },
    "com.r2studio.LoopYT": {
      "title": "LoopYT",
      "versionCode": 9,
      "description": "<div>自動刷Youtube影片</div>",
      "packageName": "com.google.android.youtube",
      "downloadURL": "https://github.com/r2-studio/robotmon-scripts/raw/master/scripts/com.r2studio.LoopYT/index.zip",
      "dependencies": [
        "https://github.com/r2-studio/robotmon-scripts/raw/master/libs/RBM-0.0.1.js",
        "https://github.com/r2-studio/robotmon-scripts/raw/master/libs/TaskController-0.0.1.js"
      ]
    },
    "com.r2studio.EZRobot": {
      "title": "EZRobot",
      "versionCode": 4,
      "description": "<div>Make your scripts yourself</div>",
      "packageName": "com.r2studio.robotmon",
      "downloadURL": "https://github.com/r2-studio/robotmon-scripts/raw/master/scripts/com.r2studio.EZRobot/index.zip",
      "dependencies": [
        "https://github.com/r2-studio/robotmon-scripts/raw/master/libs/RBM-0.0.3.js",
        "https://github.com/r2-studio/robotmon-scripts/raw/master/libs/TaskController-0.0.1.js"
      ]
    },
    "com.r2studio.LineageM": {
      "title": "Lineage M Helper",
      "versionCode": 19,
      "description": "<h1>天堂M無課救星</h1><ul><li>⭐⭐⭐大幅提升腳本速度⭐⭐⭐\n</li><li>支援所有螢幕解析度\n</li><li>自動買水買銀箭\n</li><li>HP 與 MP 條件設定使用按鈕\n</li><li>回到地圖原點\n</li><li>移動到指定地圖\n</li><li>安全區域瞬移\n</li><li>被攻擊瞬移\n</li><li>使用回卷直到安全區域\n</li><li>斷線重新連線\n</li><li>自動攻擊\n</li><li>自動使用解毒劑\n</li><li>試煉副本輔助按紐\n</li></ul>",
      "packageName": "com.gamania.lineagem",
      "downloadURL": "https://github.com/r2-studio/robotmon-scripts/raw/master/scripts/com.r2studio.LineageM/index.zip",
      "dependencies": [
        "https://github.com/r2-studio/robotmon-scripts/raw/master/libs/RBM-0.0.2.js",
        "https://github.com/r2-studio/robotmon-scripts/raw/master/libs/TaskController-0.0.1.js"
      ]
    },
    "com.donny.StoneOnline": {
      "title": "StoneOnline",
      "versionCode": 1.44,
      "description": "<div>Grow Stone online / 礦山之旅</div>",
      "packageName": "net.supercat.stone",
      "downloadURL": "https://github.com/r2-studio/robotmon-scripts/raw/master/scripts/com.donny.StoneOnline/index.zip",
      "dependencies": [
        "https://github.com/r2-studio/robotmon-scripts/raw/master/libs/RBM-0.0.3.js",
        "https://github.com/r2-studio/robotmon-scripts/raw/master/libs/TaskController-0.0.1.js" 
      ]
    },
    "com.donny.dungeonbreakers": {
      "title": "Dungeon Breaker Heroes",
      "versionCode": 0.13,
      "description": "<div>Break Drongeon Heros / 突破迷宮英雄</div>",
      "packageName": "com.linktown.dungeonbreakers",
      "downloadURL": "https://github.com/r2-studio/robotmon-scripts/raw/master/scripts/com.donny.dungeonbreakers/index.zip",
      "dependencies": [
        "https://github.com/r2-studio/robotmon-scripts/raw/master/libs/RBM-0.0.3.js",
        "https://github.com/r2-studio/robotmon-scripts/raw/master/libs/TaskController-0.0.1.js"
      ]
    },
    "com.r2studio.TapTitans2": {
      "title": "TapTitans2 automated",
      "versionCode": 8,
      "description": "<div>Make the relics rain! / 自動愛心農場!</div>",
      "packageName": "com.gamehivecorp.taptitans2",
      "downloadURL": "https://github.com/r2-studio/robotmon-scripts/raw/master/scripts/com.r2studio.TapTitans2/index.zip"
    },
    "com.r2studio.TemplateHelper": {
      "title": "Copy this and build you own game helper!",
      "versionCode": 1,
      "description": "<div>Where you start to build your own bot!</div>",
      "packageName": "com.gamehivecorp.taptitans2",
      "downloadURL": "https://github.com/r2-studio/robotmon-scripts/raw/master/scripts/com.r2studio.TemplateHelper/index.zip"
    },
    "com.cooper.FGO": {
      "title": "Fate/Grand Order",
      "versionCode": 1,
      "description": "<div>Fate/Grand Order 自動周回腳本</div>",
      "packageName": "com.xiaomeng.fategrandorder",
      "downloadURL": "https://github.com/r2-studio/robotmon-scripts/raw/master/scripts/com.cooper.FGO/index.zip"
    }
  },
  "libs": {
    "RBM-0.0.1": {
      "downloadURL": "https://github.com/r2-studio/robotmon-scripts/raw/master/libs/RBM-0.0.1.js"
    },
    "RBM-0.0.2": {
      "downloadURL": "https://github.com/r2-studio/robotmon-scripts/raw/master/libs/RBM-0.0.2.js"
    },
    "RBM-0.0.3": {
      "downloadURL": "https://github.com/r2-studio/robotmon-scripts/raw/master/libs/RBM-0.0.3.js"
    },
    "TaskController-0.0.1": {
      "downloadURL": "https://github.com/r2-studio/robotmon-scripts/raw/master/libs/TaskController-0.0.1.js"
    }
  }
}
